certifi/__init__.py
certifi/__main__.py
certifi/_patch.py
certifi/cacert.pem
certifi/core.py
certifi_system_store-3021.3.16.dist-info/LICENSE
certifi_system_store-3021.3.16.dist-info/METADATA
certifi_system_store-3021.3.16.dist-info/WHEEL
certifi_system_store-3021.3.16.dist-info/top_level.txt
certifi_system_store-3021.3.16.dist-info/zip-safe
certifi_system_store-3021.3.16.dist-info/RECORD
