Metadata-Version: 2.1
Name: certifi-system-store
Version: 3021.3.16
Summary: A certifi hack to use system trust store on Linux/FreeBSD
Home-page: https://github.com/tiran/certifi-system-store
Author: Christian Heimes
Author-email: christian@python.org
License: MPL-2.0
Project-URL: Source, https://github.com/tiran/certifi-system-store
Project-URL: Bug Tracker, https://github.com/tiran/certifi-system-store/issues
Keywords: certifi,certificates,certs,x509,tls,ssl,requests
Platform: linux
Platform: freebsd
Classifier: License :: OSI Approved :: Mozilla Public License 2.0 (MPL 2.0)
Classifier: Intended Audience :: Developers
Classifier: Programming Language :: Python :: 3
Classifier: Programming Language :: Python :: 3.6
Classifier: Programming Language :: Python :: 3.7
Classifier: Programming Language :: Python :: 3.8
Classifier: Programming Language :: Python :: 3.9
Classifier: Operating System :: POSIX :: Linux
Classifier: Operating System :: POSIX :: BSD :: FreeBSD
Classifier: Development Status :: 4 - Beta
Classifier: Topic :: Security
Provides: certifi
Obsoletes: certifi (< 3000.0)
Requires-Python: >=3.6
Requires-Dist: certifi-system-store (>4000) ; sys_platform == "win32" or sys_platform == "darwin"
Provides-Extra: lint
Requires-Dist: black ; extra == 'lint'
Requires-Dist: flake8 ; extra == 'lint'
Requires-Dist: check-manifest ; extra == 'lint'
Provides-Extra: packaging
Requires-Dist: check-manifest ; extra == 'packaging'
Provides-Extra: requests
Requires-Dist: requests ; extra == 'requests'
Provides-Extra: tests
Requires-Dist: pytest ; extra == 'tests'
